Metadata-Version: 1.1
Name: vis-sunburst-clock
Version: 0.0.2
Summary: Project Description
Home-page: UNKNOWN
Author: fusoyo <lm>
Author-email: UNKNOWN
License: MIT
Platform: UNKNOWN
Classifier: Framework :: Dash
